world/__init__.py
world/__main__.py
world/database.py
world/py.typed
world/data/__init__.py
world/data/codes.pck
world-5.2.1.dist-info/METADATA
world-5.2.1.dist-info/WHEEL
world-5.2.1.dist-info/entry_points.txt
world-5.2.1.dist-info/licenses/LICENSE
world-5.2.1.dist-info/RECORD
