Metadata-Version: 2.4
Name: world
Version: 5.2.1
Summary: world -- top level domain code mappings
Project-URL: Home Page, https://world.readthedocs.io
Project-URL: Documentation, https://world.readthedocs.io
Project-URL: Source, https://gitlab.com/warsaw/world.git
Project-URL: Bug Tracker, https://gitlab.com/warsaw/world/issues
Author-email: Barry Warsaw <barry@python.org>
License: Apache-2.0
License-File: LICENSE
Keywords: DNS,ISO 3166,country codes,domain name system
Classifier: Development Status :: 5 - Production/Stable
Classifier: Development Status :: 6 - Mature
Classifier: Intended Audience :: End Users/Desktop
Classifier: Operating System :: MacOS :: MacOS X
Classifier: Operating System :: Microsoft :: Windows
Classifier: Operating System :: POSIX
Classifier: Programming Language :: Python :: 3
Classifier: Topic :: Internet :: Name Service (DNS)
Classifier: Topic :: Software Development :: Libraries :: Python Modules
Classifier: Topic :: Utilities
Requires-Python: >=3.9
Requires-Dist: atpublic
